tfs_mt/__init__.py
tfs_mt/architecture.py
tfs_mt/data_utils.py
tfs_mt/decoding_utils.py
tfs_mt/embeddings.py
tfs_mt/training_utils.py
tfs_mt/configs/config.yml
tfs_mt/ignite_custom_utils/__init__.py
tfs_mt/ignite_custom_utils/checkpoint.py
tfs_mt/ignite_custom_utils/common.py
tfs_mt/ignite_custom_utils/trackio_logger.py
tfs_mt/ignite_custom_utils/wandb_logger.py
tfs_mt-0.1.2.dist-info/METADATA
tfs_mt-0.1.2.dist-info/WHEEL
tfs_mt-0.1.2.dist-info/licenses/LICENSE
tfs_mt-0.1.2.dist-info/RECORD
