Metadata-Version: 2.4
Name: tfs-mt
Version: 0.1.2
Summary: Transformer from scratch for Machine Translation
Project-URL: Homepage, https://giovo17.github.io/tfs-mt/
Project-URL: Repository, https://github.com/Giovo17/tfs-mt
Project-URL: Documentation, https://giovo17.github.io/tfs-mt/
Author-email: Giovanni Spadaro <giovannispada17.gs@gmail.com>
License-File: LICENSE
Keywords: deep-learning,machine-translation,nlp,nmt,pytorch,transformer
Classifier: Intended Audience :: Developers
Classifier: Intended Audience :: Education
Classifier: Programming Language :: Python
Classifier: Programming Language :: Python :: 3
Classifier: Programming Language :: Python :: 3.10
Classifier: Programming Language :: Python :: 3.11
Classifier: Programming Language :: Python :: 3.12
Classifier: Programming Language :: Python :: 3.13
Classifier: Topic :: Scientific/Engineering :: Artificial Intelligence
Classifier: Topic :: Software Development :: Libraries :: Python Modules
Requires-Python: <4.0,>=3.10
Requires-Dist: datasets>=4.0.0
Requires-Dist: jaxtyping>=0.3.3
Requires-Dist: mkdocstrings[python]>=1.0.0
Requires-Dist: omegaconf>=2.3.0
Requires-Dist: pytorch-ignite>=0.5.3
Requires-Dist: pyyaml>=6.0.2
Requires-Dist: requests>=2.32.4
Requires-Dist: tdqm>=0.0.1
Requires-Dist: torch>=2.9.0
Requires-Dist: transformers>=4.57.1
Requires-Dist: types-pyyaml>=6.0.12.20250822
Requires-Dist: types-requests>=2.32.4.20250809
Requires-Dist: zensical>=0.0.11
